[{"id":1,"first_name":"Rob","last_name":"Farrall","email":"rfarrall0@yellowpages.com","date_of_birth":"2001-10-06T17:19:44Z","age":21,"country":"China","phone":"6463742409"},
{"id":2,"first_name":"Lacee","last_name":"Dewerson","email":"ldewerson1@admin.ch","date_of_birth":"2003-05-29T11:37:57Z","age":60,"country":"Brazil","phone":"9059930851"},
{"id":3,"first_name":"Kenneth","last_name":"Kitchin","email":"kkitchin2@wikimedia.org","date_of_birth":"1985-04-26T12:26:29Z","age":26,"country":"France","phone":"7003171874"},
{"id":4,"first_name":"Scarlett","last_name":"Grigaut","email":"sgrigaut3@cloudflare.com","date_of_birth":"1970-08-15T01:30:48Z","age":48,"country":"Barbados","phone":"3004646411"},
{"id":5,"first_name":"Winston","last_name":"Yanele","email":"wyanele4@mashable.com","date_of_birth":"1983-05-15T16:14:59Z","age":47,"country":"Canada","phone":"4887591997"},
{"id":6,"first_name":"Fowler","last_name":"Alvin","email":"falvin5@google.es","date_of_birth":"1991-04-24T01:49:57Z","age":37,"country":"Japan","phone":"5764615596"},
{"id":7,"first_name":"Gladys","last_name":"Jouandet","email":"gjouandet6@slashdot.org","date_of_birth":"1972-02-28T21:04:39Z","age":24,"country":"Indonesia","phone":"1189546974"},
{"id":8,"first_name":"Wendell","last_name":"Poyntz","email":"wpoyntz7@berkeley.edu","date_of_birth":"2002-02-27T08:52:57Z","age":41,"country":"China","phone":"3019276636"},
{"id":9,"first_name":"Tamera","last_name":"Sambedge","email":"tsambedge8@addthis.com","date_of_birth":"1986-09-23T10:26:46Z","age":34,"country":"Belarus","phone":"5606814699"},
{"id":10,"first_name":"Ashla","last_name":"Schreiner","email":"aschreiner9@unicef.org","date_of_birth":"1992-02-09T08:27:16Z","age":57,"country":"China","phone":"2456329013"},
{"id":11,"first_name":"Brennen","last_name":"Pohl","email":"bpohla@bloglovin.com","date_of_birth":"2007-10-21T20:41:00Z","age":60,"country":"Russia","phone":"6183281774"},
{"id":12,"first_name":"Amie","last_name":"McGilvary","email":"amcgilvaryb@google.cn","date_of_birth":"1972-06-07T11:22:09Z","age":54,"country":"Japan","phone":"2129156979"},
{"id":13,"first_name":"Stanislaus","last_name":"Cisson","email":"scissonc@ovh.net","date_of_birth":"2003-03-31T21:48:18Z","age":56,"country":"China","phone":"5171375055"},
{"id":14,"first_name":"Penny","last_name":"Greedy","email":"pgreedyd@hao123.com","date_of_birth":"1988-06-17T23:39:41Z","age":60,"country":"Poland","phone":"7731608738"},
{"id":15,"first_name":"Toma","last_name":"Darby","email":"tdarbye@youtu.be","date_of_birth":"1998-03-06T23:43:13Z","age":35,"country":"Indonesia","phone":"6083659006"},
{"id":16,"first_name":"Faustine","last_name":"Christian","email":"fchristianf@alexa.com","date_of_birth":"1972-02-15T16:29:46Z","age":52,"country":"Russia","phone":"6857379992"},
{"id":17,"first_name":"Taddeo","last_name":"Ayrs","email":"tayrsg@reddit.com","date_of_birth":"1988-06-15T00:57:31Z","age":44,"country":"Tanzania","phone":"5905159026"},
{"id":18,"first_name":"Si","last_name":"Jerche","email":"sjercheh@webmd.com","date_of_birth":"1989-03-08T19:20:09Z","age":60,"country":"Indonesia","phone":"5993060877"},
{"id":19,"first_name":"Cash","last_name":"Bowlesworth","email":"cbowlesworthi@utexas.edu","date_of_birth":"1990-10-19T04:53:43Z","age":34,"country":"Philippines","phone":"5607797480"},
{"id":20,"first_name":"Amanda","last_name":"Barlthrop","email":"abarlthropj@mlb.com","date_of_birth":"1972-10-12T22:07:07Z","age":27,"country":"Honduras","phone":"1949889567"},
{"id":21,"first_name":"Mycah","last_name":"Rawcliffe","email":"mrawcliffek@bbc.co.uk","date_of_birth":"2009-07-01T00:38:53Z","age":35,"country":"Czech Republic","phone":"6209244260"},
{"id":22,"first_name":"Alis","last_name":"Gore","email":"agorel@addtoany.com","date_of_birth":"1996-10-04T04:29:38Z","age":55,"country":"Argentina","phone":"3181210210"},
{"id":23,"first_name":"Editha","last_name":"Hendren","email":"ehendrenm@github.io","date_of_birth":"1991-05-23T10:58:43Z","age":50,"country":"Brazil","phone":"1318584290"},
{"id":24,"first_name":"Jana","last_name":"Falconer-Taylor","email":"jfalconertaylorn@multiply.com","date_of_birth":"2001-03-30T06:46:43Z","age":39,"country":"Bolivia","phone":"8717708851"},
{"id":25,"first_name":"Kori","last_name":"Faulder","email":"kfauldero@boston.com","date_of_birth":"2001-07-14T17:03:57Z","age":44,"country":"Greece","phone":"6414974620"},
{"id":26,"first_name":"Thorvald","last_name":"Yanukhin","email":"tyanukhinp@macromedia.com","date_of_birth":"1991-10-24T08:19:42Z","age":25,"country":"United States","phone":"3606717171"},
{"id":27,"first_name":"Sarge","last_name":"Thrower","email":"sthrowerq@deviantart.com","date_of_birth":"1995-07-24T09:25:03Z","age":29,"country":"Georgia","phone":"2386776633"},
{"id":28,"first_name":"Frazier","last_name":"Fearn","email":"ffearnr@theatlantic.com","date_of_birth":"2017-02-18T19:34:59Z","age":32,"country":"Indonesia","phone":"9307673648"},
{"id":29,"first_name":"Cicely","last_name":"Aslum","email":"caslums@msn.com","date_of_birth":"1974-02-17T21:18:17Z","age":36,"country":"China","phone":"4133715534"},
{"id":30,"first_name":"Carter","last_name":"Droogan","email":"cdroogant@slate.com","date_of_birth":"2019-05-17T21:40:12Z","age":21,"country":"Greece","phone":"5836566548"},
{"id":31,"first_name":"Aubree","last_name":"Renols","email":"arenolsu@hud.gov","date_of_birth":"2008-04-23T19:17:16Z","age":46,"country":"Venezuela","phone":"5451152348"},
{"id":32,"first_name":"Bobbye","last_name":"Rydzynski","email":"brydzynskiv@irs.gov","date_of_birth":"1999-11-28T14:41:41Z","age":24,"country":"Mali","phone":"3443275901"},
{"id":33,"first_name":"Kelcy","last_name":"Stothart","email":"kstothartw@posterous.com","date_of_birth":"1978-08-30T09:15:08Z","age":34,"country":"France","phone":"7898911222"},
{"id":34,"first_name":"Aldric","last_name":"O' Scallan","email":"aoscallanx@cloudflare.com","date_of_birth":"2015-12-20T17:41:31Z","age":56,"country":"Ethiopia","phone":"2197709323"}
]